alloypythonsdk/__init__.py
alloypythonsdk/sdk.py
alloypythonsdk/sdkconfiguration.py
alloypythonsdk/_hooks/__init__.py
alloypythonsdk/_hooks/sdkhooks.py
alloypythonsdk/_hooks/types.py
alloypythonsdk/models/__init__.py
alloypythonsdk/models/components/__init__.py
alloypythonsdk/models/components/httpmetadata.py
alloypythonsdk/models/components/security.py
alloypythonsdk/models/errors/__init__.py
alloypythonsdk/models/errors/batch_create_users.py
alloypythonsdk/models/errors/complete_installation.py
alloypythonsdk/models/errors/create_a_user.py
alloypythonsdk/models/errors/credential_medata_by_app.py
alloypythonsdk/models/errors/delete_a_user.py
alloypythonsdk/models/errors/get_an_integration.py
alloypythonsdk/models/errors/get_workflow_errors.py
alloypythonsdk/models/errors/list_all_users.py
alloypythonsdk/models/errors/list_apps.py
alloypythonsdk/models/errors/list_events.py
alloypythonsdk/models/errors/list_integrations.py
alloypythonsdk/models/errors/list_users_by_workflowid.py
alloypythonsdk/models/errors/list_versions.py
alloypythonsdk/models/errors/list_workflows.py
alloypythonsdk/models/errors/sdkerror.py
alloypythonsdk/models/errors/start_installation.py
alloypythonsdk/models/errors/update_a_user.py
alloypythonsdk/models/errors/upgrade_workflow.py
alloypythonsdk/models/operations/__init__.py
alloypythonsdk/models/operations/activate_a_workflow.py
alloypythonsdk/models/operations/batch_create_users.py
alloypythonsdk/models/operations/complete_installation.py
alloypythonsdk/models/operations/create_a_credential.py
alloypythonsdk/models/operations/create_a_user.py
alloypythonsdk/models/operations/credential_medata_by_app.py
alloypythonsdk/models/operations/deactivate_a_workflow.py
alloypythonsdk/models/operations/delete_a_credential.py
alloypythonsdk/models/operations/delete_a_user.py
alloypythonsdk/models/operations/delete_logs_for_a_user.py
alloypythonsdk/models/operations/delete_workflow.py
alloypythonsdk/models/operations/disable_all_workflows_for_a_user.py
alloy_python_sdk_ai-0.0.1.dist-info/METADATA
alloy_python_sdk_ai-0.0.1.dist-info/WHEEL
alloy_python_sdk_ai-0.0.1.dist-info/top_level.txt
alloy_python_sdk_ai-0.0.1.dist-info/RECORD
